functionCacher/CacheEntry.py
functionCacher/Cacher.py
functionCacher/CompressionType.py
functionCacher/__init__.py
functionCacher/helpers.py
functionCacher-1.0.5.2.dist-info/LICENSE
functionCacher-1.0.5.2.dist-info/METADATA
functionCacher-1.0.5.2.dist-info/WHEEL
functionCacher-1.0.5.2.dist-info/top_level.txt
functionCacher-1.0.5.2.dist-info/RECORD
